pyscnomics/__init__.py
pyscnomics/pyscnomics_cli.py
pyscnomics/api/__init__.py
pyscnomics/api/adapter.py
pyscnomics/api/converter.py
pyscnomics/api/main.py
pyscnomics/api/router.py
pyscnomics/contracts/__init__.py
pyscnomics/contracts/costrecovery.py
pyscnomics/contracts/grossplit.py
pyscnomics/contracts/project.py
pyscnomics/contracts/psc_tools.py
pyscnomics/contracts/transition.py
pyscnomics/dataset/__init__.py
pyscnomics/dataset/object_sample.py
pyscnomics/dataset/sample.py
pyscnomics/econ/__init__.py
pyscnomics/econ/cashflow.py
pyscnomics/econ/costs.py
pyscnomics/econ/costs_tools.py
pyscnomics/econ/depreciation.py
pyscnomics/econ/indicator.py
pyscnomics/econ/limit.py
pyscnomics/econ/results.py
pyscnomics/econ/revenue.py
pyscnomics/econ/selection.py
pyscnomics/io/__init__.py
pyscnomics/io/aggregator.py
pyscnomics/io/config.py
pyscnomics/io/getattr.py
pyscnomics/io/parse.py
pyscnomics/io/plot_generator.py
pyscnomics/io/spreadsheet.py
pyscnomics/io/write_excel.py
pyscnomics/optimize/__init__.py
pyscnomics/optimize/adjuster.py
pyscnomics/optimize/optimization.py
pyscnomics/optimize/optimization_transition.py
pyscnomics/optimize/sensitivity.py
pyscnomics/optimize/uncertainty.py
pyscnomics/tools/__init__.py
pyscnomics/tools/helper.py
pyscnomics/tools/ltp.py
pyscnomics/tools/rpd.py
pyscnomics/tools/summarizer.py
pyscnomics/tools/summary.py
pyscnomics/tools/table.py
pyscnomics-1.4.0.dist-info/licenses/AUTHORS.md
pyscnomics-1.4.0.dist-info/licenses/LICENSE
pyscnomics-1.4.0.dist-info/METADATA
pyscnomics-1.4.0.dist-info/WHEEL
pyscnomics-1.4.0.dist-info/entry_points.txt
pyscnomics-1.4.0.dist-info/top_level.txt
pyscnomics-1.4.0.dist-info/RECORD
